fileclean/__init__.py
fileclean/clean.py
fileclean/log.py
fileclean/models.py
fileclean/setuptest.py
fileclean/view.py
fileclean/workers.py
tests/__init__.py
tests/test_clean.py
tests/test_views.py
fileclean-0.2.dist-info/LICENSE
fileclean-0.2.dist-info/METADATA
fileclean-0.2.dist-info/WHEEL
fileclean-0.2.dist-info/entry_points.txt
fileclean-0.2.dist-info/top_level.txt
fileclean-0.2.dist-info/RECORD
