Metadata-Version: 2.1
Name: fileclean
Version: 0.2
Summary: Package for clean local files
Home-page: UNKNOWN
Author: Brendon Lin
Author-email: brendon.lin@outlook.com
License: UNKNOWN
Platform: UNKNOWN
